meoteofence/__init__.py
meoteofence/hook_impl.py
meoteofence/hook_manager.py
meoteofence/hook_specs.py
meoteofence/interface.py
meoteofence/test/test_hook.py
meoteofence/test/test_interpolate.py
meoteofence/test/test_meoteofence.py
meoteofence/test/test_pluggy.py
meoteofence/test/test_query.py
meoteofence/test/test_tmp.py
shihua_meoteofence-0.1.dist-info/LICENSE
shihua_meoteofence-0.1.dist-info/METADATA
shihua_meoteofence-0.1.dist-info/WHEEL
shihua_meoteofence-0.1.dist-info/top_level.txt
shihua_meoteofence-0.1.dist-info/RECORD
